employee/__init__.py
employee/employee.py
hrm-0.0.1.dist-info/DESCRIPTION.rst
hrm-0.0.1.dist-info/METADATA
hrm-0.0.1.dist-info/RECORD
hrm-0.0.1.dist-info/WHEEL
hrm-0.0.1.dist-info/metadata.json
hrm-0.0.1.dist-info/top_level.txt
tests/__init__.py
