Metadata-Version: 2.0
Name: hrm
Version: 0.0.1
Summary: Human REsource Management
Home-page: http://packages.python.org/jag_hrm_project
Author: Jagroop Mand
Author-email: jagroop.mand@gmail.com
License: MIT
Keywords: hrm example documentation tutorial
Platform: UNKNOWN
Classifier: Topic :: Utilities
Classifier: License :: OSI Approved :: MIT License
